LICENSE
quoteran/__init__.py
quoteran/__main__.py
quoteran/core.py
quoteran/ui.py
quoteran-1.1.3.dist-info/entry_points.txt
quoteran-1.1.3.dist-info/LICENSE
quoteran-1.1.3.dist-info/WHEEL
quoteran-1.1.3.dist-info/METADATA
quoteran-1.1.3.dist-info/RECORD
