Metadata-Version: 2.1
Name: quoteran
Version: 1.1.3
Summary: Random quotes on Terminal
Home-page: https://github.com/UltiRequiem/quoteran
Keywords: commands,utilities,cli,quotes
Author: Eliaz Bobadilla
Author-email: eliaz.bobadilladev@gmail.com
Requires-Python: >=3.7,<4.0
Classifier: Programming Language :: Python :: 3
Classifier: Programming Language :: Python :: 3.7
Classifier: Programming Language :: Python :: 3.8
Classifier: Programming Language :: Python :: 3.9
Requires-Dist: colorama (>=0.4.4,<0.5.0)
Requires-Dist: requests (>=2.26.0,<3.0.0)
Project-URL: Repository, https://github.com/UltiRequiem/quoteran
